david8_postgresql/__init__.py
david8_postgresql/functions_array.py
david8_postgresql/functions_json.py
david8_postgresql/functions_str.py
david8_postgresql/core/__init__.py
david8_postgresql/core/dml.py
david8_postgresql/core/dql.py
david8_postgresql/core/functions_array_factory.py
david8_postgresql/core/functions_json_factory.py
david8_postgresql/core/query_builder.py
david8_postgresql/protocols/__init__.py
david8_postgresql/protocols/query_builder.py
david8_postgresql/protocols/sql.py
david8_postgresql-0.5.0b1.dist-info/licenses/LICENSE
david8_postgresql-0.5.0b1.dist-info/METADATA
david8_postgresql-0.5.0b1.dist-info/WHEEL
david8_postgresql-0.5.0b1.dist-info/top_level.txt
david8_postgresql-0.5.0b1.dist-info/RECORD
