Metadata-Version: 2.4
Name: david8_postgresql
Version: 0.5.0b1
Summary: SQL query builder. david8 PostgreSQL dialect
Author-email: Danila Ganchar <danila.ganchar@gmail.com>
Maintainer-email: Danila Ganchar <danila.ganchar@gmail.com>
Project-URL: Homepage, https://github.com/d-ganchar/david8_postgresql
Project-URL: Changelog, https://github.com/d-ganchar/david8_postgresql/releases
Project-URL: Issues, https://github.com/d-ganchar/david8_postgresql/issues
Project-URL: CI, https://github.com/d-ganchar/david8_postgresql/actions
Project-URL: Documentation, https://github.com/d-ganchar/david8_postgresql/wiki
Project-URL: Source, https://github.com/d-ganchar/david8_postgresql
Classifier: Development Status :: 4 - Beta
Classifier: Intended Audience :: Developers
Classifier: Topic :: Software Development :: Libraries
Classifier: Topic :: Database
Classifier: Programming Language :: Python :: 3
Classifier: Programming Language :: Python :: 3.11
Classifier: Programming Language :: Python :: 3.12
Classifier: Programming Language :: Python :: 3.13
Requires-Python: <3.14,>=3.11
License-File: LICENSE
Requires-Dist: david8<2.0.0b1,>=1.0.0b1
Dynamic: license-file
